aoc_cli_core/__init__.py
aoc_cli_core/getter.py
aoc_cli_core/initialiser.py
aoc_cli_core/opener.py
aoc_cli_core/runner.py
aoc_cli_core/submitter.py
aoc_cli_core/utils.py
aoc_cli_core/validations.py
aoc_cli_core-0.0.2.dist-info/LICENSE
aoc_cli_core-0.0.2.dist-info/METADATA
aoc_cli_core-0.0.2.dist-info/WHEEL
aoc_cli_core-0.0.2.dist-info/top_level.txt
aoc_cli_core-0.0.2.dist-info/RECORD
